pyforkurento/__init__.py
pyforkurento/base.py
pyforkurento/client.py
pyforkurento/decorator_magic.py
pyforkurento/endpoints.py
pyforkurento/exceptions.py
pyforkurento/filters.py
pyforkurento/hubs.py
pyforkurento/media_element.py
pyforkurento/parse_payloads.py
pyforkurento/pipeline.py
pyforkurento-0.1.7.dist-info/METADATA
pyforkurento-0.1.7.dist-info/RECORD
pyforkurento-0.1.7.dist-info/WHEEL
pyforkurento-0.1.7.dist-info/top_level.txt
