Metadata-Version: 2.1
Name: pyforkurento
Version: 0.1.7
Summary: A Python client for Kurento Media Server
Home-page: https://github.com/kelvingakuo/pyforkurento
Author: Kelvin Gakuo
Author-email: kelvingakuo@gmail.com
License: MIT
Platform: UNKNOWN
Requires-Dist: websocket-client (==0.57.0)
